llama_index/llms/azure_openai/__init__.py
llama_index/llms/azure_openai/base.py
llama_index/llms/azure_openai/utils.py
flying_delta_llms_azure_openai-0.1.0.dist-info/METADATA
flying_delta_llms_azure_openai-0.1.0.dist-info/WHEEL
flying_delta_llms_azure_openai-0.1.0.dist-info/RECORD
